{
  "criteria": {
    "requirement": {
      "trigger": "minecraft:player_interacted_with_entity",
      "conditions": {
        "entity": {
          "nbt": "{Tags:[\"energyutils.copper_servo\"]}"
        },
        "player": [
          {
            "condition": "minecraft:value_check",
            "value": {
              "type": "minecraft:score",
              "target": {
                "type": "minecraft:fixed",
                "name": "#energyutils.major"
              },
              "score": "load.status"
            },
            "range": 1
          },
          {
            "condition": "minecraft:value_check",
            "value": {
              "type": "minecraft:score",
              "target": {
                "type": "minecraft:fixed",
                "name": "#energyutils.minor"
              },
              "score": "load.status"
            },
            "range": 0
          },
          {
            "condition": "minecraft:value_check",
            "value": {
              "type": "minecraft:score",
              "target": {
                "type": "minecraft:fixed",
                "name": "#energyutils.patch"
              },
              "score": "load.status"
            },
            "range": 0
          }
        ]
      }
    }
  },
  "rewards": {
    "function": "energyutils:calls/click_copper_servo"
  }
}
